mylib_023/__init__.py
mylib_023-0.1.dist-info/LICENSE.txt
mylib_023-0.1.dist-info/METADATA
mylib_023-0.1.dist-info/WHEEL
mylib_023-0.1.dist-info/top_level.txt
mylib_023-0.1.dist-info/RECORD
