Metadata-Version: 2.1
Name: mylib-023
Version: 0.1
Summary: for calculating square
Author: Mr.Nikhil Patil
Author-email: nikhilpatil30397@gmail.com
Classifier: Programming Language :: Python :: 3
Classifier: License :: OSI Approved :: MIT License
Classifier: Operating System :: OS Independent
License-File: LICENSE.txt
